[
  {
    "id": 1,
    "name": "University of Dhaka",
    "website": "www.du.ac.bd",
    "img": "https://media.istockphoto.com/photos/bangladesh-dhaka-picture-id620981310?k=20&m=620981310&s=612x612&w=0&h=z7ofjMwc2wqjX37XTQw0zvuat-PuXgQFDHzDIlMvjmY="
  },
  {
    "id": 2,
    "name": "University of Rajshahi",
    "website": "www.ru.ac.bd"
  },
  {
    "id": 3,
    "name": "Bangladesh Agricultural University",
    "website": "www.bau.edu.bd"
  },
  {
    "id": 4,
    "name": "Bangladesh University of Engineering & Technology",
    "website": "www.buet.ac.bd"
  },
  {
    "id": 5,
    "name": "University of Chittagong",
    "website": "www.cu.ac.bd"
  }
]